top_pr/__init__.py
top_pr/mode_drop.py
top_pr/top_pr.py
top_pr-0.2.1.dist-info/LICENSE
top_pr-0.2.1.dist-info/METADATA
top_pr-0.2.1.dist-info/WHEEL
top_pr-0.2.1.dist-info/top_level.txt
top_pr-0.2.1.dist-info/RECORD
