Metadata-Version: 2.1
Name: top-pr
Version: 0.2.1
Summary: TopP&R: Robust Support Estimation Approach for Evaluating Fidelity and Diversity in Generative Models.
Home-page: https://github.com/LAIT-CVLab/TopPR
Author: Pumjun Kim
Keywords: toppr,evaluation metric,topological metric,precision and recall
Classifier: Programming Language :: Python :: 3
Classifier: License :: OSI Approved :: MIT License
Classifier: Operating System :: OS Independent
License-File: LICENSE
Requires-Dist: torch
Requires-Dist: torchvision
Requires-Dist: numpy
Requires-Dist: scikit-learn
Requires-Dist: scipy
Requires-Dist: tqdm
Requires-Dist: matplotlib
Requires-Dist: gudhi
